oxylabs/__init__.py
oxylabs/_version.py
oxylabs/internal/__init__.py
oxylabs/internal/api.py
oxylabs/internal/client.py
oxylabs/proxy/__init__.py
oxylabs/proxy/proxy.py
oxylabs/sources/__init__.py
oxylabs/sources/response.py
oxylabs/sources/amazon/__init__.py
oxylabs/sources/amazon/amazon.py
oxylabs/sources/bing/__init__.py
oxylabs/sources/bing/bing.py
oxylabs/sources/google/__init__.py
oxylabs/sources/google/google.py
oxylabs/sources/google_shopping/__init__.py
oxylabs/sources/google_shopping/google_shopping.py
oxylabs/sources/kroger/__init__.py
oxylabs/sources/kroger/kroger.py
oxylabs/sources/universal/__init__.py
oxylabs/sources/universal/universal.py
oxylabs/sources/wayfair/__init__.py
oxylabs/sources/wayfair/wayfair.py
oxylabs/sources/youtube_transcript/__init__.py
oxylabs/sources/youtube_transcript/youtube_transcript.py
oxylabs/utils/__init__.py
oxylabs/utils/defaults.py
oxylabs/utils/utils.py
oxylabs/utils/types/__init__.py
oxylabs/utils/types/domain.py
oxylabs/utils/types/fn_name.py
oxylabs/utils/types/locale.py
oxylabs/utils/types/render.py
oxylabs/utils/types/source.py
oxylabs/utils/types/user_agent_type.py
oxylabs-2.0.0.dist-info/licenses/LICENSE
oxylabs-2.0.0.dist-info/METADATA
oxylabs-2.0.0.dist-info/WHEEL
oxylabs-2.0.0.dist-info/top_level.txt
oxylabs-2.0.0.dist-info/RECORD
