Metadata-Version: 2.4
Name: oxylabs
Version: 2.0.0
Summary: Official Python library for Oxylabs Scraper APIs
Home-page: https://oxylabs.io/
Author: Oxylabs
Author-email: support@oxylabs.io
License: MIT
License-File: LICENSE
Requires-Dist: aiohttp
Requires-Dist: requests
Dynamic: author
Dynamic: author-email
Dynamic: description
Dynamic: home-page
Dynamic: license
Dynamic: license-file
Dynamic: requires-dist
Dynamic: summary
